llama_index/embeddings/google/__init__.py
llama_index/embeddings/google/gemini.py
llama_index/embeddings/google/palm.py
llama_index/embeddings/google/univ_sent_encoder.py
llama_index_embeddings_google-0.4.2.dist-info/METADATA
llama_index_embeddings_google-0.4.2.dist-info/WHEEL
llama_index_embeddings_google-0.4.2.dist-info/licenses/LICENSE
llama_index_embeddings_google-0.4.2.dist-info/RECORD
